README.md
setup.cfg
setup.py
gplog/__init__.py
gplog/gplog.py
gplog.egg-info/PKG-INFO
gplog.egg-info/SOURCES.txt
gplog.egg-info/dependency_links.txt
gplog.egg-info/not-zip-safe
gplog.egg-info/top_level.txt