Metadata-Version: 1.0
Name: gplog
Version: 0.0
Summary: Easy and readable logging!!
Home-page: UNKNOWN
Author: UNKNOWN
Author-email: gotsalyuk.pasha@yandex.ru
License: UNKNOWN
Platform: UNKNOWN
